python_package_14410/__init__.py
python_package_14410/calculation.py
math_module_14410-0.0.1.dist-info/METADATA
math_module_14410-0.0.1.dist-info/WHEEL
math_module_14410-0.0.1.dist-info/top_level.txt
math_module_14410-0.0.1.dist-info/RECORD
