Metadata-Version: 2.4
Name: Math_module_14410
Version: 0.0.1
Summary: A test python package for class assignment
Dynamic: description
Dynamic: description-content-type
Dynamic: summary
